pornhubSpider/__init__.py
pornhubSpider-1.1.2.dist-info/LICENSE
pornhubSpider-1.1.2.dist-info/METADATA
pornhubSpider-1.1.2.dist-info/WHEEL
pornhubSpider-1.1.2.dist-info/top_level.txt
pornhubSpider-1.1.2.dist-info/RECORD
