Metadata-Version: 2.1
Name: pornhubSpider
Version: 1.1.2
Summary: A simple spider of Pornhub
Home-page: https://github.com/ZoinkCN/pornhubSpider
Author: ZoinkCN
Author-email: zoinkcn@outlook.com
License: UNKNOWN
Platform: UNKNOWN
Classifier: Programming Language :: Python :: 3
Classifier: License :: OSI Approved :: MIT License
Classifier: Operating System :: OS Independent
Requires-Python: >=3.8
Requires-Dist: requests
Requires-Dist: Js2Py
Requires-Dist: beautifulsoup4
Requires-Dist: lxml
